utcp_http/__init__.py
utcp_http/http_call_template.py
utcp_http/http_communication_protocol.py
utcp_http/openapi_converter.py
utcp_http/sse_call_template.py
utcp_http/sse_communication_protocol.py
utcp_http/streamable_http_call_template.py
utcp_http/streamable_http_communication_protocol.py
utcp_http-1.0.5.dist-info/METADATA
utcp_http-1.0.5.dist-info/WHEEL
utcp_http-1.0.5.dist-info/entry_points.txt
utcp_http-1.0.5.dist-info/top_level.txt
utcp_http-1.0.5.dist-info/RECORD
